.pre-commit-config.yaml
AUTHORS.rst
CHANGES.rst
CONTRIBUTING.rst
LICENSE.rst
MANIFEST.in
README.rst
noxfile.py
pyproject.toml
requirements-develop.txt
requirements-testing.txt
requirements.txt
setup.cfg
setup.py
baked_brie.egg-info/PKG-INFO
baked_brie.egg-info/SOURCES.txt
baked_brie.egg-info/dependency_links.txt
baked_brie.egg-info/requires.txt
baked_brie.egg-info/top_level.txt
brie/__init__.py
brie/_version.py
brie/alongshore_transporter.py
brie/brie.py
brie/brie_bmi.py
brie/waves.py
scripts/plot_brie_colorgrid.py
scripts/plot_brie_matlab.py
scripts/run_brie_parallel.py
tests/test_alongshore_transport.py
tests/test_bmi.py
tests/test_brie_matlab.py
tests/test_wave_generator.py
tests/test_bmi/brie.yaml
tests/test_brie_matlab/test_brie_matlab_seed.mat