Metadata-Version: 2.1
Name: baked-brie
Version: 1.0.0b1.dev0
Summary: The Barrier Inlet Environment (BRIE) Model
Author: Katherine Anarde
Author-email: kanarde@ncsu.edu
Maintainer: Katherine Anarde
Maintainer-email: kanarde@ncsu.edu
License: The MIT License (MIT)
Project-URL: homepage, https://github.com/UNC-CECL/brie
Project-URL: documentation, https://github.com/UNC-CECL/brie
Project-URL: repository, https://github.com/UNC-CECL/brie
Project-URL: changelog, https://raw.githubusercontent.com/UNC-CECL/brie/master-brie/CHANGES.rst
Keywords: earth science,coast,barrier inlet
Classifier: Development Status :: 4 - Beta
Classifier: Intended Audience :: Science/Research
Classifier: License :: OSI Approved :: MIT License
Classifier: Operating System :: OS Independent
Classifier: Programming Language :: Python :: 3
Classifier: Programming Language :: Python :: 3.8
Classifier: Programming Language :: Python :: 3.9
Classifier: Programming Language :: Python :: 3.10
Classifier: Programming Language :: Python :: 3.11
Classifier: Programming Language :: Python :: 3 :: Only
Classifier: Topic :: Scientific/Engineering :: Physics
Requires-Python: >=3.8
Provides-Extra: dev
License-File: LICENSE.rst
License-File: AUTHORS.rst
